nmappalyzer/__init__.py
nmappalyzer/main.py
nmappalyzer/test.py
nmappalyzer-1.0.3.dist-info/LICENSE
nmappalyzer-1.0.3.dist-info/WHEEL
nmappalyzer-1.0.3.dist-info/METADATA
nmappalyzer-1.0.3.dist-info/RECORD
